.gitignore
CHANGELOG.rst
MANIFEST.in
README.rst
bootstrap.py
buildout.cfg
setup.cfg
setup.py
src/elementtreewriter/__init__.py
src/elementtreewriter/tests.py
src/elementtreewriter/xmlwriter.py
src/elementtreewriter/xmlwriter.txt
src/elementtreewriter.egg-info/PKG-INFO
src/elementtreewriter.egg-info/SOURCES.txt
src/elementtreewriter.egg-info/dependency_links.txt
src/elementtreewriter.egg-info/pbr.json
src/elementtreewriter.egg-info/requires.txt
src/elementtreewriter.egg-info/top_level.txt
src/elementtreewriter.egg-info/zip-safe