Metadata-Version: 1.1
Name: elementtreewriter
Version: 1.2
Summary: XML writer for elementtree with sane namespace support.
Home-page: UNKNOWN
Author: Martin Raspe, Jens Klein
Author-email: hertzhaft@biblhertz.it, jens@bluedynamics.com
License: D-FSL - German Free Software License
Keywords: xml elementtree
Platform: UNKNOWN
Classifier: Operating System :: OS Independent
Classifier: Programming Language :: Python
Classifier: Development Status :: 5 - Production/Stable
Classifier: Topic :: Software Development :: Libraries :: Python Modules
Classifier: Topic :: Text Processing :: Markup :: XML
